smetana/__init__.py
smetana/interface.py
smetana/legacy.py
smetana/smetana.py
smetana-1.2.1.data/scripts/smetana
smetana-1.2.1.dist-info/licenses/LICENSE
smetana-1.2.1.dist-info/METADATA
smetana-1.2.1.dist-info/WHEEL
smetana-1.2.1.dist-info/top_level.txt
smetana-1.2.1.dist-info/RECORD
