Metadata-Version: 2.4
Name: smetana
Version: 1.2.1
Summary: Species METabolic interaction ANAlysis (SMETANA) is a python-based command line tool to analyse microbial communities.
Home-page: https://github.com/cdanielmachado/smetana
Author: Daniel Machado
Author-email: cdanielmachado@gmail.com
License: Apache Software License 2.0
Keywords: smetana
Classifier: Development Status :: 5 - Production/Stable
Classifier: Environment :: Console
Classifier: Intended Audience :: Science/Research
Classifier: Topic :: Scientific/Engineering :: Bio-Informatics
Classifier: Programming Language :: Python :: 3.8
Classifier: Programming Language :: Python :: 3.9
Classifier: Programming Language :: Python :: 3.10
Classifier: Programming Language :: Python :: 3.11
Classifier: Programming Language :: Python :: 3.12
Classifier: License :: OSI Approved :: Apache Software License
License-File: LICENSE
Requires-Dist: reframed>=1.6.0
Requires-Dist: pandas>=2.0.0
Dynamic: author
Dynamic: author-email
Dynamic: classifier
Dynamic: description
Dynamic: home-page
Dynamic: keywords
Dynamic: license
Dynamic: license-file
Dynamic: requires-dist
Dynamic: summary
